README.md
setup.py
zohocrm/__init__.py
zohocrm/api.py
zohocrm_api.egg-info/PKG-INFO
zohocrm_api.egg-info/SOURCES.txt
zohocrm_api.egg-info/dependency_links.txt
zohocrm_api.egg-info/requires.txt
zohocrm_api.egg-info/top_level.txt