Metadata-Version: 1.2
Name: zohocrm-api
Version: 0.0.5
Summary: ZOHOCRM rest api wrapper
Home-page: https://github.com/bzdvdn/zohocrm-api
Author: bzdvdn
Author-email: bzdv.dn@gmail.com
License: MIT
Platform: UNKNOWN
Requires-Python: >=3.6
